tasktiger_admin/__init__.py
tasktiger_admin/integrations.py
tasktiger_admin/utils.py
tasktiger_admin/views.py
tasktiger_admin/templates/tasktiger_admin/tasktiger.html
tasktiger_admin/templates/tasktiger_admin/tasktiger_queue_detail.html
tasktiger_admin/templates/tasktiger_admin/tasktiger_task_detail.html
tasktiger_admin-0.3.1.dist-info/METADATA
tasktiger_admin-0.3.1.dist-info/WHEEL
tasktiger_admin-0.3.1.dist-info/entry_points.txt
tasktiger_admin-0.3.1.dist-info/top_level.txt
tasktiger_admin-0.3.1.dist-info/RECORD
