Metadata-Version: 2.1
Name: tasktiger-admin
Version: 0.3.1
Summary: Admin for tasktiger, a Python task queue
Home-page: http://github.com/closeio/tasktiger-admin
Author: UNKNOWN
Author-email: UNKNOWN
License: MIT
Platform: any
Classifier: Intended Audience :: Developers
Classifier: License :: OSI Approved :: MIT License
Classifier: Operating System :: OS Independent
Classifier: Topic :: Software Development :: Libraries :: Python Modules
Classifier: Programming Language :: Python
Classifier: Programming Language :: Python :: 2
Classifier: Programming Language :: Python :: 2.7
Classifier: Programming Language :: Python :: 3
Classifier: Programming Language :: Python :: 3.5
Classifier: Programming Language :: Python :: 3.6
Classifier: Framework :: Flask
Requires-Dist: click
Requires-Dist: flask-admin
Requires-Dist: redis (<3,>=2)
Requires-Dist: structlog
Requires-Dist: tasktiger (>=0.10.1)
